translatefree/__init__.py
translatefree/translate.py
translatefree-1.0.9.dist-info/LICENSE
translatefree-1.0.9.dist-info/METADATA
translatefree-1.0.9.dist-info/WHEEL
translatefree-1.0.9.dist-info/top_level.txt
translatefree-1.0.9.dist-info/RECORD
